pynnet/__init__.py
pynnet/activation.py
pynnet/loss.py
pynnet/network.py
pynnet/optimizer.py
pynnet/layers/__init__.py
pynnet/layers/base.py
pynnet/layers/dense.py
pynnet-0.0.2.dist-info/licenses/LICENSE
pynnet-0.0.2.dist-info/METADATA
pynnet-0.0.2.dist-info/WHEEL
pynnet-0.0.2.dist-info/top_level.txt
pynnet-0.0.2.dist-info/RECORD
